polyexpose/__init__.py
polyexpose/polyexpose.py
polyexpose/common/__init__.py
polyexpose/common/constants.py
polyexpose/common/utils.py
polyexpose/data/__init__.py
polyexpose/data/userdata.parquet
polyexpose/spark_templates/__init__.py
polyexpose/spark_templates/create_sample_table.py
polyexpose/spark_templates/exec_sql.py
polyexpose/spark_templates/export_bigquery.py
polyexpose/spark_templates/export_csv.py
polyexpose/spark_templates/show_catalog.py
polyexpose/spark_templates/stream_pubsub.py
polyexpose-0.0.5.data/data/polyexpose/userdata.parquet
polyexpose-0.0.5.dist-info/LICENSE.md
polyexpose-0.0.5.dist-info/METADATA
polyexpose-0.0.5.dist-info/WHEEL
polyexpose-0.0.5.dist-info/top_level.txt
polyexpose-0.0.5.dist-info/RECORD
