Metadata-Version: 2.1
Name: polyexpose
Version: 0.0.5
Summary: polyexpose
Home-page: UNKNOWN
Author: Luis Velasco
Author-email: <luis.velasco@gmail.com>
License: UNKNOWN
Keywords: python,polyexpose
Platform: UNKNOWN
Classifier: Development Status :: 3 - Alpha
Classifier: Intended Audience :: Education
Classifier: Programming Language :: Python :: 3
Classifier: Operating System :: MacOS :: MacOS X
Classifier: Operating System :: Microsoft :: Windows
Requires-Dist: google-cloud-dataproc
Requires-Dist: google-cloud-storage
Requires-Dist: pyspark (~=3.3.0)
Requires-Dist: pyyaml
Requires-Dist: google-cloud-pubsublite (==1.4.2)
Requires-Dist: protobuf
Requires-Dist: requests
